MANIFEST.in
README.txt
setup.py
docs/HISTORY.txt
docs/INSTALL.txt
docs/LICENSE.GPL
docs/LICENSE.txt
quintagroup/__init__.py
quintagroup.doublecolumndocument.egg-info/PKG-INFO
quintagroup.doublecolumndocument.egg-info/SOURCES.txt
quintagroup.doublecolumndocument.egg-info/dependency_links.txt
quintagroup.doublecolumndocument.egg-info/entry_points.txt
quintagroup.doublecolumndocument.egg-info/namespace_packages.txt
quintagroup.doublecolumndocument.egg-info/not-zip-safe
quintagroup.doublecolumndocument.egg-info/requires.txt
quintagroup.doublecolumndocument.egg-info/top_level.txt
quintagroup/doublecolumndocument/__init__.py
quintagroup/doublecolumndocument/config.py
quintagroup/doublecolumndocument/configure.zcml
quintagroup/doublecolumndocument/browser/__init__.py
quintagroup/doublecolumndocument/browser/configure.zcml
quintagroup/doublecolumndocument/browser/doublecolumndocument_view.pt
quintagroup/doublecolumndocument/browser/resources/doublecolumndocument.css
quintagroup/doublecolumndocument/content/__init__.py
quintagroup/doublecolumndocument/content/configure.zcml
quintagroup/doublecolumndocument/content/doublecolumndocument.py
quintagroup/doublecolumndocument/content/interfaces.py
quintagroup/doublecolumndocument/i18n/quintagroup.doublecolumndocument-uk.po
quintagroup/doublecolumndocument/i18n/quintagroup.doublecolumndocument.pot
quintagroup/doublecolumndocument/profiles/default/cssregistry.xml
quintagroup/doublecolumndocument/profiles/default/factorytool.xml
quintagroup/doublecolumndocument/profiles/default/metadata.xml
quintagroup/doublecolumndocument/profiles/default/types.xml
quintagroup/doublecolumndocument/profiles/default/types/DoubleColumnDocument.xml