Metadata-Version: 1.0
Name: quintagroup.doublecolumndocument
Version: 0.2
Summary: Extends Document with one more extra column
Home-page: http://quintagroup.com/services/plone-development/products/
Author: (c) "Quintagroup"
Author-email: support@quintagroup.com
License: GPL
Keywords: plone content archetypes document doublecolumn
Platform: UNKNOWN
Classifier: Framework :: Plone
Classifier: Intended Audience :: Developers
Classifier: Topic :: Software Development :: Libraries :: Python Modules
Classifier: License :: OSI Approved :: GNU General Public License (GPL)
